{
    "data": [
      {
        "date": "09/23/2016",
        "subject": "Demand Alert",
        "to": "All Drivers",
        "type": "All"
      },
      {
        "date": "09/23/2016",
        "subject": "Demand Alert",
        "to": "All Drivers",
        "type": "All"
      },
      {
        "date": "09/23/2016",
        "subject": "Demand Alert",
        "to": "All Drivers",
        "type": "All"
      },
      {
        "date": "09/23/2016",
        "subject": "Demand Alert",
        "to": "All Drivers",
        "type": "All"
      },
      {
        "date": "09/23/2016",
        "subject": "Demand Alert",
        "to": "All Drivers",
        "type": "All"
      },
      {
        "date": "09/23/2016",
        "subject": "Demand Alert",
        "to": "All Drivers",
        "type": "All"
      }
    ]

}